{"cameraMode":{"drawMode":0,"name":"Shaded","section":"Shading Mode"},"sceneLighting":true,"audioPlay":false,"sceneViewState":{"m_AlwaysRefresh":false,"showFog":true,"showSkybox":true,"showFlares":true,"showImageEffects":true,"showParticleSystems":true,"showVisualEffectGraphs":true,"m_FxEnabled":true},"in2DMode":false,"pivot":{"x":-10.61186408996582,"y":-20.647319793701173,"z":-75.16352081298828},"rotation":{"x":0.24886789917945863,"y":-0.7258284091949463,"z":0.3255957067012787,"w":0.5538434982299805},"size":33.07377243041992,"orthographic":false}